{
  "basicInfo": {
    "itemName": "실버케어AI",
    "oneLiner": "AI 음성분석으로 독거노인의 건강 이상을 조기 감지하는 스마트 돌봄 서비스",
    "targetCustomer": "독거노인 및 그 가족, 지자체 돌봄센터",
    "industry": "bio_healthcare",
    "fundingAmount": 10000,
    "templateType": "yebi-chogi"
  },
  "sectionData": {
    "problem": {
      "market_status": "[시장 현황]\n국내 65세 이상 고령인구는 2024년 기준 950만명으로 전체 인구의 18.4%를 차지합니다(통계청, 2024). 이 중 독거노인은 약 180만 가구로, 매년 8%씩 증가하고 있습니다.\n\n고령화 속도는 OECD 국가 중 1위이며, 2025년에는 초고령사회(20% 이상)에 진입할 것으로 전망됩니다. 독거노인 돌봄 시장 규모는 2024년 기준 약 3조원으로 추정되며, 연평균 15% 성장 중입니다.\n\n정부는 '어르신 돌봄 디지털 전환' 정책을 통해 2025년까지 AI 기반 돌봄 서비스 확대를 추진 중입니다.",
      "problem_definition": "[핵심 문제점]\n독거노인의 78%가 건강 이상 발생 시 24시간 이내에 발견되지 못하고 있습니다(보건복지부, 2024).\n\n1. 조기 감지 실패: 독거노인의 뇌졸중, 심장질환 등 응급상황 발생 시 평균 발견 시간 18시간\n   - 골든타임(4시간) 내 발견율 23% 불과\n   - 이로 인한 사망률 일반 대비 3.2배 높음\n\n2. 기존 돌봄의 한계:\n   - 방문 돌봄: 주 1-2회, 1회 30분 (커버리지 부족)\n   - 응급호출기: 의식 있을 때만 작동 (무의식 상태 대응 불가)\n   - 영상 모니터링: 프라이버시 침해 우려로 거부율 67%\n\n3. 돌봄 인력 부족:\n   - 2024년 사회복지사 1인당 담당 노인 수: 평균 127명\n   - 실질적 케어 가능 인원: 30명 미만",
      "development_necessity": "[개발 필요성]\n음성 기반 AI 건강 모니터링 기술 개발이 시급한 이유:\n\n1. 기술적 필요성\n   - 음성에서 우울증, 파킨슨병 조기 징후 감지 정확도 89% 달성 (MIT 연구, 2023)\n   - 프라이버시를 침해하지 않으면서 24시간 모니터링 가능\n   - 기존 스마트 스피커 인프라 활용 가능 (추가 기기 불필요)\n\n2. 사회적 필요성\n   - 초고령사회 대비 비용 효율적 돌봄 시스템 구축 필수\n   - 독거노인 고독사 연간 3,000건 이상 (경찰청, 2024)\n   - 지자체 돌봄 예산 한계로 효율적 솔루션 수요 급증\n\n3. 시장 기회\n   - 정부 디지털 돌봄 예산 2025년 5,000억원 편성\n   - 글로벌 시니어케어 AI 시장 2027년 150억 달러 전망"
    },
    "solution": {
      "development_plan": "[솔루션 개요]\n실버케어AI는 음성 분석 AI를 통해 독거노인의 건강 상태를 24시간 모니터링하고, 이상 징후 발생 시 즉시 보호자와 돌봄센터에 알림을 전송하는 서비스입니다.\n\n[작동 방식]\n1단계: 음성 수집 → 스마트 스피커를 통해 일상 대화/인사 음성 수집\n2단계: AI 분석 → 음성 패턴, 말 속도, 호흡 분석으로 건강 상태 진단\n3단계: 알림 전송 → 이상 감지 시 가족/돌봄센터 앱으로 즉시 알림\n4단계: 대응 연계 → 119 자동 연결, 방문 돌봄 트리거\n\n[개발 로드맵]\n- 1~3개월: 음성 분석 AI 모델 고도화 (정확도 92% 목표)\n- 4~6개월: 스마트 스피커 연동 앱 개발, 파일럿 테스트 (100가구)\n- 7~10개월: 지자체 연계 실증, 서비스 런칭\n\n[현재 개발 현황]\n- MVP 완료: 음성 분석 AI 모델 v1.0 (정확도 85%)\n- 파일럿: 서울시 마포구 독거노인 30가구 테스트 중\n- 만족도: 4.2/5.0 (참여 어르신 설문)",
      "differentiation": "[차별화 포인트]\n\n1. 비침습적 모니터링\n   - 카메라 없이 음성만으로 건강 상태 파악\n   - 프라이버시 보호로 수용성 89% (경쟁사 CCTV 방식 33%)\n\n2. 독자 AI 기술\n   - 한국어 노인 음성 특화 모델 (10만 시간 학습 데이터)\n   - 사투리, 발음 불분명 음성도 95% 인식\n   - 특허 출원 완료 (출원번호: 10-2024-0012345)\n\n3. 기존 인프라 활용\n   - 신규 기기 설치 불필요 (기존 스마트 스피커 연동)\n   - 초기 비용 0원, 월 구독료만 발생\n\n4. 돌봄 생태계 연계\n   - 지자체 돌봄센터 시스템 API 연동\n   - 119 자동 연결 기능 탑재\n   - 병원/약국 예약 연계 예정",
      "competitiveness": "[경쟁력 분석]\n\nvs. A사 (CCTV 모니터링)\n- A사: 월 5만원, 프라이버시 우려로 설치 거부 67%\n- 우리: 월 2만원, 음성 기반으로 수용성 89%\n\nvs. B사 (웨어러블 기기)\n- B사: 기기 구매 30만원 + 월 3만원, 착용 거부율 54%\n- 우리: 기기 구매 0원 + 월 2만원, 일상 대화만으로 측정\n\n[핵심 기술 경쟁력]\n- 음성 기반 우울증 감지 정확도: 89% (업계 최고)\n- 낙상 감지 정확도: 94%\n- 응급상황 감지 후 알림까지 소요 시간: 평균 12초\n\n[파트너십]\n- 서울디지털재단 MOU 체결 (2024.06)\n- 마포구청 돌봄센터 연계 시범사업 진행 중\n- SKT 스마트홈 연동 협의 중"
    },
    "scaleup": {
      "business_model": "[수익 모델]\n\n1. B2C 구독 서비스 (40%)\n   - Basic: 월 19,000원 (음성 모니터링 + 알림)\n   - Premium: 월 39,000원 (+ 건강리포트 + 의료상담 연계)\n\n2. B2G 라이선스 (50%)\n   - 지자체 돌봄센터 API 연동: 인당 월 5,000원\n   - 관제 대시보드 제공: 센터당 월 50만원\n\n3. B2B 제휴 (10%)\n   - 보험사 연계: 실버보험 가입자 대상 서비스 제공\n   - 통신사 연계: 시니어폰 요금제 번들\n\n[Unit Economics]\n- CAC (고객획득비용): 35,000원\n- LTV (고객생애가치): 456,000원 (평균 24개월 구독)\n- LTV/CAC: 13.0\n- 월 손익분기점: 가입자 3,000명",
      "market_size": "[시장 규모 분석]\n\nTAM (전체 시장): 3조원\n- 국내 독거노인 돌봄 서비스 시장 전체\n- 출처: 보건복지부 고령화 실태조사, 2024\n\nSAM (유효 시장): 6,000억원\n- 디지털/AI 기반 돌봄 서비스 시장\n- TAM의 20%\n- 연평균 성장률 25%\n\nSOM (목표 시장): 120억원\n- 3년 내 점유 목표: 2%\n- 가입 가구 수 목표: 50,000가구\n- 지자체 계약 목표: 50개 구청\n\n[시장 동향]\n- 정부 디지털 돌봄 예산: 2025년 5,000억원 (전년 대비 40% 증가)\n- AI 시니어케어 글로벌 시장: 2027년 150억 달러 (CAGR 18%)\n- 경쟁 강도: 중간 (본격적 AI 돌봄 서비스 부재)",
      "roadmap": "[사업화 로드맵]\n\n1단계: 시장 진입 (0-6개월)\n- 타겟: 서울/경기 지자체 돌봄센터\n- 전략: 무료 파일럿 → 성과 입증 → 정식 계약\n- KPI: 파일럿 10개 구청, 사용자 1,000명\n\n2단계: 성장 (6-12개월)\n- 타겟: 전국 지자체 + B2C 확대\n- 전략: 성공 사례 기반 영업, 온라인 마케팅\n- KPI: 계약 30개 구청, 가입자 10,000명, MRR 2억원\n\n3단계: 확장 (12-24개월)\n- 타겟: 보험사/통신사 제휴, 해외 진출\n- 전략: B2B 파트너십, 일본 시장 진출\n- KPI: ARR 50억원, 해외 매출 비중 10%\n\n[마일스톤]\n- 2025.06: 정식 서비스 런칭\n- 2025.09: 시리즈A 투자 유치 (30억원 목표)\n- 2025.12: 가입자 20,000명 달성\n- 2026.06: 일본 시장 진출"
    },
    "team": {
      "founder": "김건강 | CEO & Founder\n- 서울대학교 의료정보학 석사\n- 前 삼성전자 헬스케어사업부 PM (5년)\n- 前 스타트업 A사 공동창업 (Exit)\n- AI 헬스케어 분야 특허 3건 보유\n\n[핵심 성과]\n- 삼성헬스 시니어 모드 기획/런칭 (MAU 50만 달성)\n- AI 건강진단 알고리즘 개발 (정확도 91%)\n- 창업 경진대회 대상 수상 (2023 K-스타트업)\n\n[창업 동기]\n할머니의 갑작스러운 낙상 사고 후 3일만에 발견된 경험이 창업의 계기가 되었습니다.",
      "team_members": "이기술 | CTO\n- KAIST 인공지능대학원 석사\n- 前 네이버 AI랩 음성인식팀 (4년)\n- 음성 AI 관련 논문 5편, 특허 2건\n- 담당: 음성 분석 AI 개발, 기술 총괄\n\n박마케팅 | CMO\n- 연세대 경영학과\n- 前 토스 Growth팀 (3년)\n- B2C 마케팅 캠페인 다수 성공\n- 담당: 마케팅 전략, 사업개발\n\n최개발 | Lead Developer\n- 고려대 컴퓨터공학과\n- 前 카카오 백엔드 개발자 (3년)\n- 담당: 백엔드 개발, 인프라 구축\n\n[자문단]\n- 서울대 의대 노인의학과 교수\n- 삼성전자 前 헬스케어사업부장\n- 한국사회복지협의회 부회장",
      "team_synergy": "왜 이 팀인가?\n1. 도메인 전문성: 대표의 헬스케어 사업 경험 + CTO의 음성 AI 기술력\n2. 실행력: 전원 스타트업/빅테크 경험으로 빠른 MVP 개발\n3. 네트워크: 지자체, 대기업, 의료계 연결 가능\n\n보완 계획\n- 6개월 내 사회복지사 출신 CS 매니저 1명 채용\n- 영업/파트너십 담당자 1명 채용 예정\n- AI 엔지니어 2명 추가 채용 계획"
    }
  },
  "schedule": [
    {
      "no": "1",
      "content": "AI 음성 분석 모델 고도화",
      "period": "25.03 ~ 25.05",
      "detail": "정확도 85% → 92% 목표"
    },
    {
      "no": "2",
      "content": "스마트 스피커 연동 앱 개발",
      "period": "25.04 ~ 25.07",
      "detail": "iOS/Android 앱 개발"
    },
    {
      "no": "3",
      "content": "파일럿 테스트 (100가구)",
      "period": "25.06 ~ 25.08",
      "detail": "서울 마포구/성동구 진행"
    },
    {
      "no": "4",
      "content": "지자체 연계 실증사업",
      "period": "25.08 ~ 25.10",
      "detail": "10개 구청 파일럿"
    },
    {
      "no": "5",
      "content": "정식 서비스 런칭",
      "period": "25.10 ~ 25.12",
      "detail": "B2C + B2G 동시 출시"
    }
  ],
  "budget": [
    {
      "category": "재료비",
      "detail": "서버 및 클라우드 인프라 구축",
      "amount": "15,000,000"
    },
    {
      "category": "재료비",
      "detail": "AI 학습 데이터 구매",
      "amount": "10,000,000"
    },
    {
      "category": "외주용역비",
      "detail": "앱 UI/UX 디자인 외주",
      "amount": "8,000,000"
    },
    {
      "category": "외주용역비",
      "detail": "보안 인증 컨설팅",
      "amount": "5,000,000"
    },
    {
      "category": "인건비",
      "detail": "AI 엔지니어 인건비 (6개월)",
      "amount": "42,000,000"
    },
    {
      "category": "지급수수료",
      "detail": "특허 출원 비용",
      "amount": "3,000,000"
    },
    {
      "category": "마케팅비",
      "detail": "파일럿 홍보 및 마케팅",
      "amount": "7,000,000"
    }
  ],
  "teamTable": [
    {
      "no": "1",
      "position": "대표이사",
      "role": "총괄 기획, 사업개발",
      "capability": "의료정보학 석사, 삼성전자 PM 5년",
      "status": "완료('24.01)"
    },
    {
      "no": "2",
      "position": "CTO",
      "role": "AI 개발 총괄",
      "capability": "KAIST AI대학원, 네이버 AI랩 4년",
      "status": "완료('24.03)"
    },
    {
      "no": "3",
      "position": "CMO",
      "role": "마케팅/영업",
      "capability": "연세대 경영, 토스 Growth 3년",
      "status": "완료('24.06)"
    },
    {
      "no": "4",
      "position": "개발자",
      "role": "백엔드 개발",
      "capability": "고려대 컴공, 카카오 3년",
      "status": "완료('24.09)"
    },
    {
      "no": "5",
      "position": "AI 엔지니어",
      "role": "음성 AI 모델 개발",
      "capability": "관련 경력 3년 이상",
      "status": "예정('25.06)"
    }
  ],
  "partners": [
    {
      "no": "1",
      "name": "서울디지털재단",
      "capability": "디지털 복지 인프라",
      "plan": "파일럿 테스트 지원",
      "period": "25.06"
    },
    {
      "no": "2",
      "name": "마포구청",
      "capability": "독거노인 돌봄센터 운영",
      "plan": "실증사업 협력",
      "period": "25.08"
    },
    {
      "no": "3",
      "name": "SKT",
      "capability": "스마트홈 플랫폼",
      "plan": "스피커 연동 기술 협력",
      "period": "25.09"
    }
  ]
}